alembic_bot/main.py
alembic_bot-1.4.dist-info/METADATA
alembic_bot-1.4.dist-info/WHEEL
alembic_bot-1.4.dist-info/entry_points.txt
alembic_bot-1.4.dist-info/top_level.txt
alembic_bot-1.4.dist-info/RECORD
